{"newspaper": "Giornale d’Italia", "date_of_article": "1906", "original_snippet_context": "Discussion of a bill related to currency conversion.", "relevant_quote": "O projecto de lei [...] para prorrogar até 31 de [...] tinam a converter atorlando a circulação, foi hoje approvado.", "classification": "Neutral/Factual", "justification": "The text reports the approval of a bill related to an ongoing conversion process affecting currency circulation, without expressing an opinion on the Caixa de Conversão itself.", "confidence": "Medium"}