{"newspaper": "Jornal do Commercio", "date_of_article": "1906", "original_snippet_context": "Discussing a loan secured by the State of São Paulo and its relation to the Convênio de Taubaté and coffee valorization.", "relevant_quote": "A' propaganda desabrida que foi feito contra o projecto dos tres presidentes, o estrangeiro responde confiando os seus capitaes ao Estado que pugna com maior ardor pela valorização do café e fixação do cambio.", "classification": "Clearly Expansionist", "justification": "The successful loan is presented as foreign validation of the Convênio de Taubaté, which included the \"fixação do cambio\" (exchange rate stabilization) as part of coffee valorization, a key expansionist aim.", "confidence": "High"}