{"newspaper": null, "date_of_article": "1906", "original_snippet_context": "An article discussing the Argentine Caixa de Conversão and its relevance to the Brazilian context.", "relevant_quote": "Passou quasi despercebida em nosso paiz a noticia de haver sido creada a caixa de conversão argentina, no fim do 1899. A situação financeira do Brazil era, então, péssima e os esforços communs convergiam para a valorisação do meio circulante. A febre cambial alarmava os homens investidos do poder e provocava a formula de planos reveladores. Apesar disso, ninguém se lembrou—no governo, no Congresso, em imprensa—de transplantar para cá a maravilha platina, e seguimos o rumo traçado pelo programma do quadrienio Campista-Salles.", "classification": "Leaning Expansionist", "justification": "The author notes Brazil's poor financial situation in 1899 and the focus on valorizing the currency, suggesting a missed opportunity in not adopting a conversion model like Argentina's, which aligns with expansionist aims of using such a system for monetary improvement.", "confidence": "Medium"}