{"newspaper": null, "date_of_article": "1906", "original_snippet_context": null, "relevant_quote": "O Sr. Paula Ramos, citando o exemplo da Republica Argentina, diz que alli a Caixa de Conversão fez otristissima figura» nos dous primeiros annos de funecionamento, e que só os saldos reaes da exportação puderam fazel-a forte dos cem milhões celebrados em março deste anno. Ora, dos próprios algarismos citados, e bem conhecidos, pelo illustre deputado, ve ribra-se que não foi triste assim a figura j feita pela Caixa de Conversão.", "classification": "Neutral/Factual", "justification": "The text presents arguments from both sides (initial criticism of the Caixa's performance followed by a counter-argument), making it primarily a presentation of differing views without a clear authorial stance.", "confidence": "Medium"}